{
    "key": "group_5b0ec58a3413b",
    "title": "Overview Sections",
    "fields": [
        {
            "key": "field_5b0ec932b8cf2",
            "label": "Preview Sections",
            "name": "overview_preview_sections",
            "type": "repeater",
            "instructions": "Build out customizable page sections to link to the various sub-pages within each overview page",
            "required": 1,
            "conditional_logic": 0,
            "wrapper": {
                "width": "",
                "class": "",
                "id": ""
            },
            "collapsed": "field_5b0ec9d9b8cf4",
            "min": 0,
            "max": 5,
            "layout": "row",
            "button_label": "",
            "sub_fields": [
                {
                    "key": "field_5b0ec9d9b8cf4",
                    "label": "Preview Link",
                    "name": "overview_preview_link",
                    "type": "post_object",
                    "instructions": "",
                    "required": 0,
                    "conditional_logic": 0,
                    "wrapper": {
                        "width": "",
                        "class": "",
                        "id": ""
                    },
                    "post_type": [
                        "page"
                    ],
                    "taxonomy": [],
                    "allow_null": 0,
                    "multiple": 0,
                    "return_format": "id",
                    "ui": 1
                },
                {
                    "key": "field_5b0ec945b8cf3",
                    "label": "Preview Text",
                    "name": "overview_preview_text",
                    "type": "wysiwyg",
                    "instructions": "",
                    "required": 1,
                    "conditional_logic": 0,
                    "wrapper": {
                        "width": "",
                        "class": "",
                        "id": ""
                    },
                    "default_value": "",
                    "tabs": "all",
                    "toolbar": "full",
                    "media_upload": 0,
                    "delay": 1
                },
                {
                    "key": "field_5b0eca24b8cf5",
                    "label": "Use Custom Gallery",
                    "name": "overview_use_custom_gallery",
                    "type": "true_false",
                    "instructions": "",
                    "required": 0,
                    "conditional_logic": 0,
                    "wrapper": {
                        "width": "",
                        "class": "",
                        "id": ""
                    },
                    "message": "",
                    "default_value": 0,
                    "ui": 0,
                    "ui_on_text": "",
                    "ui_off_text": ""
                },
                {
                    "key": "field_5b0eca5fb8cf6",
                    "label": "Custom Gallery",
                    "name": "overview_custom_gallery",
                    "type": "gallery",
                    "instructions": "",
                    "required": 0,
                    "conditional_logic": [
                        [
                            {
                                "field": "field_5b0eca24b8cf5",
                                "operator": "==",
                                "value": "1"
                            }
                        ]
                    ],
                    "wrapper": {
                        "width": "",
                        "class": "",
                        "id": ""
                    },
                    "min": 1,
                    "max": 3,
                    "insert": "append",
                    "library": "all",
                    "min_width": "",
                    "min_height": "",
                    "min_size": "",
                    "max_width": "",
                    "max_height": "",
                    "max_size": "",
                    "mime_types": ""
                }
            ]
        }
    ],
    "location": [
        [
            {
                "param": "page_template",
                "operator": "==",
                "value": "page-overview.php"
            }
        ]
    ],
    "menu_order": 0,
    "position": "normal",
    "style": "default",
    "label_placement": "left",
    "instruction_placement": "field",
    "hide_on_screen": [
        "excerpt",
        "author",
        "send-trackbacks"
    ],
    "active": 1,
    "description": "",
    "modified": 1528483844
}